README.txt
setup.cfg
setup.py
docs/HISTORY.txt
docs/INSTALL.txt
docs/LICENSE.GPL
docs/LICENSE.txt
icnews/__init__.py
icnews.core.egg-info/PKG-INFO
icnews.core.egg-info/SOURCES.txt
icnews.core.egg-info/dependency_links.txt
icnews.core.egg-info/entry_points.txt
icnews.core.egg-info/namespace_packages.txt
icnews.core.egg-info/not-zip-safe
icnews.core.egg-info/requires.txt
icnews.core.egg-info/top_level.txt
icnews/core/README.txt
icnews/core/__init__.py
icnews/core/config.py
icnews/core/configure.zcml
icnews/core/interfaces.py
icnews/core/revision.txt
icnews/core/setuphandlers.py
icnews/core/version.txt
icnews/core/Extensions/__init__.py
icnews/core/Extensions/install.py
icnews/core/browser/__init__.py
icnews/core/browser/admin.py
icnews/core/browser/admin.zcml
icnews/core/browser/configure.zcml
icnews/core/browser/images/logo16-icnews.png
icnews/core/browser/templates/admin-overview.pt
icnews/core/browser/templates/settings-template.pt
icnews/core/profiles/default/actionicons.xml
icnews/core/profiles/default/controlpanel.xml
icnews/core/profiles/default/import_steps.xml
icnews/core/tests/__init__.py
icnews/core/tests/base.py
icnews/core/tests/test_setup.py