Metadata-Version: 1.0
Name: icnews.core
Version: 1.0-dev-r319
Summary: icNews.Core
Home-page: www.platecom.com
Author: Inter-Cultura Consultora SRL - Ibai Sistemas SA - Eusko Ikaskuntza-Sociedad de Estudios Vascos
Author-email: dev@inter-cultura.com
License: GPL
Platform: UNKNOWN
Classifier: Framework :: Plone
Classifier: Framework :: Zope2
Classifier: Framework :: Zope3
Classifier: Programming Language :: Python
Classifier: Topic :: Software Development :: Libraries :: Python Modules
